{
  "--alpha-loss": "0.2",
  "--bert-lr": "2e-5",
  "--checkpoint-path": "2022-07-19-16:59:59.pt",
  "--dev-path": "''",
  "--eval-batch-size": "32",
  "--ffn-lr": "0.001",
  "--help": false,
  "--lang": "English",
  "--loss-type": "cross-entropy",
  "--max-epoch": "20",
  "--max-length": "128",
  "--output-dropout": "0.1",
  "--seed": "42",
  "--train-batch-size": "32",
  "--train-path": "''"
}{
  "--alpha-loss": "0.2",
  "--bert-lr": "2e-5",
  "--checkpoint-path": "2022-07-19-17:59:07.pt",
  "--dev-path": "E:\\Spanemotion\\SpanEmo-master\\SpanEmo-master\\data\\2018-E-c-En-dev.txt",
  "--eval-batch-size": "32",
  "--ffn-lr": "0.001",
  "--help": false,
  "--lang": "English",
  "--loss-type": "cross-entropy",
  "--max-epoch": "20",
  "--max-length": "128",
  "--output-dropout": "0.1",
  "--seed": "42",
  "--train-batch-size": "32",
  "--train-path": "E:\\Spanemotion\\SpanEmo-master\\SpanEmo-master\\data\\2018-E-c-En-train.txt"
}{
  "--alpha-loss": "0.2",
  "--bert-lr": "2e-5",
  "--checkpoint-path": "2022-07-19-18:24:13.pt",
  "--dev-path": "E:\\Spanemotion\\SpanEmo-master\\SpanEmo-master\\data\\2018-E-c-En-dev.txt",
  "--eval-batch-size": "32",
  "--ffn-lr": "0.001",
  "--help": false,
  "--lang": "English",
  "--loss-type": "cross-entropy",
  "--max-epoch": "20",
  "--max-length": "128",
  "--output-dropout": "0.1",
  "--seed": "42",
  "--train-batch-size": "32",
  "--train-path": "E:\\Spanemotion\\SpanEmo-master\\SpanEmo-master\\data\\2018-E-c-En-train.txt"
}{
  "--alpha-loss": "0.2",
  "--bert-lr": "2e-5",
  "--checkpoint-path": "2022-07-19-19:41:35.pt",
  "--dev-path": "E:\\Spanemotion\\SpanEmo-master\\SpanEmo-master\\data\\2018-E-c-En-dev.txt",
  "--eval-batch-size": "32",
  "--ffn-lr": "0.001",
  "--help": false,
  "--lang": "English",
  "--loss-type": "cross-entropy",
  "--max-epoch": "20",
  "--max-length": "128",
  "--output-dropout": "0.1",
  "--seed": "42",
  "--train-batch-size": "4",
  "--train-path": "E:\\Spanemotion\\SpanEmo-master\\SpanEmo-master\\data\\2018-E-c-En-train.txt"
}{
  "--alpha-loss": "0.2",
  "--bert-lr": "2e-5",
  "--checkpoint-path": "2022-07-20-09:13:52.pt",
  "--dev-path": "E:\\Spanemotion\\SpanEmo-master\\SpanEmo-master\\data\\dev.txt",
  "--eval-batch-size": "32",
  "--ffn-lr": "0.001",
  "--help": false,
  "--lang": "English",
  "--loss-type": "cross-entropy",
  "--max-epoch": "20",
  "--max-length": "128",
  "--output-dropout": "0.1",
  "--seed": "42",
  "--train-batch-size": "4",
  "--train-path": "E:\\Spanemotion\\SpanEmo-master\\SpanEmo-master\\data\\train.txt"
}{
  "--alpha-loss": "0.2",
  "--bert-lr": "2e-5",
  "--checkpoint-path": "2022-07-20-09:19:48.pt",
  "--dev-path": "E:\\Spanemotion\\SpanEmo-master\\SpanEmo-master\\data\\dev.txt",
  "--eval-batch-size": "32",
  "--ffn-lr": "0.001",
  "--help": false,
  "--lang": "English",
  "--loss-type": "cross-entropy",
  "--max-epoch": "20",
  "--max-length": "128",
  "--output-dropout": "0.1",
  "--seed": "42",
  "--train-batch-size": "4",
  "--train-path": "E:\\Spanemotion\\SpanEmo-master\\SpanEmo-master\\data\\train.txt"
}{
  "--alpha-loss": "0.2",
  "--bert-lr": "2e-5",
  "--checkpoint-path": "2022-07-20-09:23:40.pt",
  "--dev-path": "E:\\Spanemotion\\SpanEmo-master\\SpanEmo-master\\data\\dev.txt",
  "--eval-batch-size": "32",
  "--ffn-lr": "0.001",
  "--help": false,
  "--lang": "English",
  "--loss-type": "cross-entropy",
  "--max-epoch": "20",
  "--max-length": "128",
  "--output-dropout": "0.1",
  "--seed": "42",
  "--train-batch-size": "4",
  "--train-path": "E:\\Spanemotion\\SpanEmo-master\\SpanEmo-master\\data\\train.txt"
}{
  "--alpha-loss": "0.2",
  "--bert-lr": "2e-5",
  "--checkpoint-path": "2022-07-20-09:28:58.pt",
  "--dev-path": "E:\\Spanemotion\\SpanEmo-master\\SpanEmo-master\\data\\dev.txt",
  "--eval-batch-size": "32",
  "--ffn-lr": "0.001",
  "--help": false,
  "--lang": "English",
  "--loss-type": "cross-entropy",
  "--max-epoch": "20",
  "--max-length": "128",
  "--output-dropout": "0.1",
  "--seed": "42",
  "--train-batch-size": "4",
  "--train-path": "E:\\Spanemotion\\SpanEmo-master\\SpanEmo-master\\data\\train.txt"
}{
  "--alpha-loss": "0.2",
  "--bert-lr": "2e-5",
  "--checkpoint-path": "2022-07-20-10:42:51.pt",
  "--dev-path": "E:\\Spanemotion\\SpanEmo-master\\SpanEmo-master\\data\\dev.txt",
  "--eval-batch-size": "32",
  "--ffn-lr": "0.001",
  "--help": false,
  "--lang": "English",
  "--loss-type": "cross-entropy",
  "--max-epoch": "20",
  "--max-length": "128",
  "--output-dropout": "0.1",
  "--seed": "42",
  "--train-batch-size": "4",
  "--train-path": "E:\\Spanemotion\\SpanEmo-master\\SpanEmo-master\\data\\train.txt"
}{
  "--alpha-loss": "0.2",
  "--bert-lr": "2e-5",
  "--checkpoint-path": "2022-07-21-12:20:52.pt",
  "--dev-path": "E:\\Spanemotion\\SpanEmo-master\\SpanEmo-master\\data\\dev.txt",
  "--eval-batch-size": "32",
  "--ffn-lr": "0.001",
  "--help": false,
  "--lang": "English",
  "--loss-type": "cross-entropy",
  "--max-epoch": "20",
  "--max-length": "128",
  "--output-dropout": "0.1",
  "--seed": "42",
  "--train-batch-size": "4",
  "--train-path": "E:\\Spanemotion\\SpanEmo-master\\SpanEmo-master\\data\\train.txt"
}{
  "--alpha-loss": "0.2",
  "--bert-lr": "2e-5",
  "--checkpoint-path": "2022-07-21-12:23:53.pt",
  "--dev-path": "E:\\Spanemotion\\SpanEmo-master\\SpanEmo-master\\data\\dev.txt",
  "--eval-batch-size": "32",
  "--ffn-lr": "0.001",
  "--help": false,
  "--lang": "English",
  "--loss-type": "cross-entropy",
  "--max-epoch": "20",
  "--max-length": "128",
  "--output-dropout": "0.1",
  "--seed": "42",
  "--train-batch-size": "4",
  "--train-path": "E:\\Spanemotion\\SpanEmo-master\\SpanEmo-master\\data\\train.txt"
}{
  "--alpha-loss": "0.2",
  "--bert-lr": "2e-5",
  "--checkpoint-path": "2022-07-21-12:27:32.pt",
  "--dev-path": "E:\\Spanemotion\\SpanEmo-master\\SpanEmo-master\\data\\dev.txt",
  "--eval-batch-size": "32",
  "--ffn-lr": "0.001",
  "--help": false,
  "--lang": "English",
  "--loss-type": "cross-entropy",
  "--max-epoch": "20",
  "--max-length": "128",
  "--output-dropout": "0.1",
  "--seed": "42",
  "--train-batch-size": "4",
  "--train-path": "E:\\Spanemotion\\SpanEmo-master\\SpanEmo-master\\data\\train.txt"
}{
  "--alpha-loss": "0.2",
  "--bert-lr": "2e-5",
  "--checkpoint-path": "2022-07-21-12:42:35.pt",
  "--dev-path": "E:\\Spanemotion\\SpanEmo-master\\SpanEmo-master\\data\\dev.txt",
  "--eval-batch-size": "32",
  "--ffn-lr": "0.001",
  "--help": false,
  "--lang": "English",
  "--loss-type": "cross-entropy",
  "--max-epoch": "20",
  "--max-length": "128",
  "--output-dropout": "0.1",
  "--seed": "42",
  "--train-batch-size": "4",
  "--train-path": "E:\\Spanemotion\\SpanEmo-master\\SpanEmo-master\\data\\train.txt"
}{
  "--alpha-loss": "0.2",
  "--bert-lr": "2e-5",
  "--checkpoint-path": "2022-07-21-12:44:30.pt",
  "--dev-path": "E:\\Spanemotion\\SpanEmo-master\\SpanEmo-master\\data\\dev.txt",
  "--eval-batch-size": "32",
  "--ffn-lr": "0.001",
  "--help": false,
  "--lang": "English",
  "--loss-type": "cross-entropy",
  "--max-epoch": "20",
  "--max-length": "128",
  "--output-dropout": "0.1",
  "--seed": "42",
  "--train-batch-size": "4",
  "--train-path": "E:\\Spanemotion\\SpanEmo-master\\SpanEmo-master\\data\\train.txt"
}{
  "--alpha-loss": "0.2",
  "--bert-lr": "2e-5",
  "--checkpoint-path": "2022-07-21-12:45:49.pt",
  "--dev-path": "E:\\Spanemotion\\SpanEmo-master\\SpanEmo-master\\data\\dev.txt",
  "--eval-batch-size": "32",
  "--ffn-lr": "0.001",
  "--help": false,
  "--lang": "English",
  "--loss-type": "cross-entropy",
  "--max-epoch": "20",
  "--max-length": "128",
  "--output-dropout": "0.1",
  "--seed": "42",
  "--train-batch-size": "4",
  "--train-path": "E:\\Spanemotion\\SpanEmo-master\\SpanEmo-master\\data\\train.txt"
}{
  "--alpha-loss": "0.2",
  "--bert-lr": "2e-5",
  "--checkpoint-path": "2022-07-23-21:44:16.pt",
  "--dev-path": "E:\\Spanemotion\\SpanEmo-master\\SpanEmo-master\\data\\dev.txt",
  "--eval-batch-size": "32",
  "--ffn-lr": "0.001",
  "--help": false,
  "--lang": "English",
  "--loss-type": "cross-entropy",
  "--max-epoch": "20",
  "--max-length": "128",
  "--output-dropout": "0.1",
  "--seed": "42",
  "--train-batch-size": "4",
  "--train-path": "E:\\Spanemotion\\SpanEmo-master\\SpanEmo-master\\data\\train.txt"
}{
  "--alpha-loss": "0.2",
  "--bert-lr": "2e-5",
  "--checkpoint-path": "2022-07-23-22:02:01.pt",
  "--dev-path": "E:\\Spanemotion\\SpanEmo-master\\SpanEmo-master\\data\\dev.txt",
  "--eval-batch-size": "32",
  "--ffn-lr": "0.001",
  "--help": false,
  "--lang": "English",
  "--loss-type": "cross-entropy",
  "--max-epoch": "20",
  "--max-length": "128",
  "--output-dropout": "0.1",
  "--seed": "42",
  "--train-batch-size": "4",
  "--train-path": "E:\\Spanemotion\\SpanEmo-master\\SpanEmo-master\\data\\train.txt"
}{
  "--alpha-loss": "0.2",
  "--bert-lr": "2e-5",
  "--checkpoint-path": "2022-07-23-22:02:37.pt",
  "--dev-path": "E:\\Spanemotion\\SpanEmo-master\\SpanEmo-master\\data\\dev.txt",
  "--eval-batch-size": "32",
  "--ffn-lr": "0.001",
  "--help": false,
  "--lang": "English",
  "--loss-type": "cross-entropy",
  "--max-epoch": "20",
  "--max-length": "128",
  "--output-dropout": "0.1",
  "--seed": "42",
  "--train-batch-size": "4",
  "--train-path": "E:\\Spanemotion\\SpanEmo-master\\SpanEmo-master\\data\\train.txt"
}{
  "--alpha-loss": "0.2",
  "--bert-lr": "2e-5",
  "--checkpoint-path": "2022-07-23-22:07:33.pt",
  "--dev-path": "E:\\Spanemotion\\SpanEmo-master\\SpanEmo-master\\data\\dev.txt",
  "--eval-batch-size": "32",
  "--ffn-lr": "0.001",
  "--help": false,
  "--lang": "English",
  "--loss-type": "cross-entropy",
  "--max-epoch": "20",
  "--max-length": "128",
  "--output-dropout": "0.1",
  "--seed": "42",
  "--train-batch-size": "4",
  "--train-path": "E:\\Spanemotion\\SpanEmo-master\\SpanEmo-master\\data\\train.txt"
}{
  "--alpha-loss": "0.2",
  "--bert-lr": "2e-5",
  "--checkpoint-path": "2022-07-23-22:08:06.pt",
  "--dev-path": "E:\\Spanemotion\\SpanEmo-master\\SpanEmo-master\\data\\dev.txt",
  "--eval-batch-size": "32",
  "--ffn-lr": "0.001",
  "--help": false,
  "--lang": "English",
  "--loss-type": "cross-entropy",
  "--max-epoch": "20",
  "--max-length": "128",
  "--output-dropout": "0.1",
  "--seed": "42",
  "--train-batch-size": "4",
  "--train-path": "E:\\Spanemotion\\SpanEmo-master\\SpanEmo-master\\data\\train.txt"
}{
  "--alpha-loss": "0.2",
  "--bert-lr": "2e-5",
  "--checkpoint-path": "2022-07-23-22:09:38.pt",
  "--dev-path": "E:\\Spanemotion\\SpanEmo-master\\SpanEmo-master\\data\\dev.txt",
  "--eval-batch-size": "32",
  "--ffn-lr": "0.001",
  "--help": false,
  "--lang": "English",
  "--loss-type": "cross-entropy",
  "--max-epoch": "20",
  "--max-length": "128",
  "--output-dropout": "0.1",
  "--seed": "42",
  "--train-batch-size": "4",
  "--train-path": "E:\\Spanemotion\\SpanEmo-master\\SpanEmo-master\\data\\train.txt"
}{
  "--alpha-loss": "0.2",
  "--bert-lr": "2e-5",
  "--checkpoint-path": "2022-07-23-22:10:04.pt",
  "--dev-path": "E:\\Spanemotion\\SpanEmo-master\\SpanEmo-master\\data\\dev.txt",
  "--eval-batch-size": "32",
  "--ffn-lr": "0.001",
  "--help": false,
  "--lang": "English",
  "--loss-type": "cross-entropy",
  "--max-epoch": "20",
  "--max-length": "128",
  "--output-dropout": "0.1",
  "--seed": "42",
  "--train-batch-size": "4",
  "--train-path": "E:\\Spanemotion\\SpanEmo-master\\SpanEmo-master\\data\\train.txt"
}{
  "--alpha-loss": "0.2",
  "--bert-lr": "2e-5",
  "--checkpoint-path": "2022-07-23-22:11:50.pt",
  "--dev-path": "E:\\Spanemotion\\SpanEmo-master\\SpanEmo-master\\data\\dev.txt",
  "--eval-batch-size": "32",
  "--ffn-lr": "0.001",
  "--help": false,
  "--lang": "English",
  "--loss-type": "cross-entropy",
  "--max-epoch": "20",
  "--max-length": "128",
  "--output-dropout": "0.1",
  "--seed": "42",
  "--train-batch-size": "4",
  "--train-path": "E:\\Spanemotion\\SpanEmo-master\\SpanEmo-master\\data\\train.txt"
}{
  "--checkpoint-path": "2022-07-23-22:21:09.pt",
  "--dev-path": "E:\\Spanemotion\\SpanEmo-master\\SpanEmo-master\\data\\dev.txt",
  "--train-batch-size": "4",
  "--train-path": "E:\\Spanemotion\\SpanEmo-master\\SpanEmo-master\\data\\train.txt"
}{
  "--alpha-loss": "0.2",
  "--bert-lr": "2e-5",
  "--checkpoint-path": "2022-07-23-22:26:48.pt",
  "--dev-path": "E:\\Spanemotion\\SpanEmo-master\\SpanEmo-master\\data\\dev.txt",
  "--eval-batch-size": "32",
  "--ffn-lr": "0.001",
  "--help": false,
  "--lang": "English",
  "--loss-type": "cross-entropy",
  "--max-epoch": "20",
  "--max-length": "128",
  "--output-dropout": "0.1",
  "--seed": "42",
  "--train-batch-size": "4",
  "--train-path": "E:\\Spanemotion\\SpanEmo-master\\SpanEmo-master\\data\\train.txt"
}{
  "--alpha-loss": "0.2",
  "--bert-lr": "2e-5",
  "--checkpoint-path": "2022-07-23-22:27:47.pt",
  "--dev-path": "E:\\Spanemotion\\SpanEmo-master\\SpanEmo-master\\data\\dev.txt",
  "--eval-batch-size": "32",
  "--ffn-lr": "0.001",
  "--help": false,
  "--lang": "English",
  "--loss-type": "cross-entropy",
  "--max-epoch": "20",
  "--max-length": "128",
  "--output-dropout": "0.1",
  "--seed": "42",
  "--train-batch-size": "4",
  "--train-path": "E:\\Spanemotion\\SpanEmo-master\\SpanEmo-master\\data\\train.txt"
}{
  "--alpha-loss": "0.2",
  "--bert-lr": "2e-5",
  "--checkpoint-path": "2022-07-23-22:29:28.pt",
  "--dev-path": "E:\\Spanemotion\\SpanEmo-master\\SpanEmo-master\\data\\dev.txt",
  "--eval-batch-size": "32",
  "--ffn-lr": "0.001",
  "--help": false,
  "--lang": "English",
  "--loss-type": "cross-entropy",
  "--max-epoch": "20",
  "--max-length": "128",
  "--output-dropout": "0.1",
  "--seed": "42",
  "--train-batch-size": "4",
  "--train-path": "E:\\Spanemotion\\SpanEmo-master\\SpanEmo-master\\data\\train.txt"
}{
  "--alpha-loss": "0.2",
  "--bert-lr": "2e-5",
  "--checkpoint-path": "2022-07-23-22:30:54.pt",
  "--dev-path": "E:\\Spanemotion\\SpanEmo-master\\SpanEmo-master\\data\\dev.txt",
  "--eval-batch-size": "32",
  "--ffn-lr": "0.001",
  "--help": false,
  "--lang": "English",
  "--loss-type": "cross-entropy",
  "--max-epoch": "20",
  "--max-length": "128",
  "--output-dropout": "0.1",
  "--seed": "42",
  "--train-batch-size": "4",
  "--train-path": "E:\\Spanemotion\\SpanEmo-master\\SpanEmo-master\\data\\train.txt"
}{
  "--alpha-loss": "0.2",
  "--bert-lr": "2e-5",
  "--checkpoint-path": "2022-07-25-20:09:17.pt",
  "--dev-path": "E:\\Spanemotion\\SpanEmo-master\\SpanEmo-LIWC\\data\\dev.txt",
  "--eval-batch-size": "32",
  "--ffn-lr": "0.001",
  "--help": false,
  "--lang": "English",
  "--loss-type": "cross-entropy",
  "--max-epoch": "20",
  "--max-length": "128",
  "--output-dropout": "0.1",
  "--seed": "42",
  "--train-batch-size": "4",
  "--train-path": "E:\\Spanemotion\\SpanEmo-master\\SpanEmo-LIWC\\data\\train.txt"
}{
  "--alpha-loss": "0.2",
  "--bert-lr": "2e-5",
  "--checkpoint-path": "2022-07-25-20:11:53.pt",
  "--dev-path": "E:\\Spanemotion\\SpanEmo-master\\SpanEmo-LIWC\\data-feature\\dev-sentiment.txt",
  "--eval-batch-size": "32",
  "--ffn-lr": "0.001",
  "--help": false,
  "--lang": "English",
  "--loss-type": "cross-entropy",
  "--max-epoch": "20",
  "--max-length": "128",
  "--output-dropout": "0.1",
  "--seed": "42",
  "--train-batch-size": "4",
  "--train-path": "E:\\Spanemotion\\SpanEmo-master\\SpanEmo-LIWC\\data-feature\\train-sentiment.txt"
}{
  "--alpha-loss": "0.2",
  "--bert-lr": "2e-5",
  "--checkpoint-path": "2022-07-25-20:22:59.pt",
  "--dev-path": "E:\\Spanemotion\\SpanEmo-master\\SpanEmo-LIWC\\data-feature\\dev-sentiment.txt",
  "--eval-batch-size": "32",
  "--ffn-lr": "0.001",
  "--help": false,
  "--lang": "English",
  "--loss-type": "cross-entropy",
  "--max-epoch": "20",
  "--max-length": "128",
  "--output-dropout": "0.1",
  "--seed": "42",
  "--train-batch-size": "4",
  "--train-path": "E:\\Spanemotion\\SpanEmo-master\\SpanEmo-LIWC\\data-feature\\train-sentiment.txt"
}{
  "--alpha-loss": "0.2",
  "--bert-lr": "2e-5",
  "--checkpoint-path": "2022-07-25-20:24:37.pt",
  "--dev-path": "E:\\Spanemotion\\SpanEmo-master\\SpanEmo-LIWC\\data-feature\\dev-sentiment.txt",
  "--eval-batch-size": "32",
  "--ffn-lr": "0.001",
  "--help": false,
  "--lang": "English",
  "--loss-type": "cross-entropy",
  "--max-epoch": "20",
  "--max-length": "128",
  "--output-dropout": "0.1",
  "--seed": "42",
  "--train-batch-size": "4",
  "--train-path": "E:\\Spanemotion\\SpanEmo-master\\SpanEmo-LIWC\\data-feature\\train-sentiment.txt"
}{
  "--alpha-loss": "0.2",
  "--bert-lr": "2e-5",
  "--checkpoint-path": "2022-07-25-20:33:57.pt",
  "--dev-path": "E:\\Spanemotion\\SpanEmo-master\\SpanEmo-LIWC\\data-feature\\dev-sentiment.txt",
  "--eval-batch-size": "32",
  "--ffn-lr": "0.001",
  "--help": false,
  "--lang": "English",
  "--loss-type": "cross-entropy",
  "--max-epoch": "20",
  "--max-length": "128",
  "--output-dropout": "0.1",
  "--seed": "42",
  "--train-batch-size": "32",
  "--train-path": "E:\\Spanemotion\\SpanEmo-master\\SpanEmo-LIWC\\data-feature\\train-sentiment.txt"
}{
  "--alpha-loss": "0.2",
  "--bert-lr": "2e-5",
  "--checkpoint-path": "2022-07-25-20:35:44.pt",
  "--dev-path": "E:\\Spanemotion\\SpanEmo-master\\SpanEmo-LIWC\\data-feature\\dev-sentiment.txt",
  "--eval-batch-size": "32",
  "--ffn-lr": "0.001",
  "--help": false,
  "--lang": "English",
  "--loss-type": "cross-entropy",
  "--max-epoch": "20",
  "--max-length": "128",
  "--output-dropout": "0.1",
  "--seed": "42",
  "--train-batch-size": "32",
  "--train-path": "E:\\Spanemotion\\SpanEmo-master\\SpanEmo-LIWC\\data-feature\\train-sentiment.txt"
}{
  "--alpha-loss": "0.2",
  "--bert-lr": "2e-5",
  "--checkpoint-path": "2022-07-25-20:54:55.pt",
  "--dev-path": "E:\\Spanemotion\\SpanEmo-master\\SpanEmo-LIWC\\data-feature\\dev-sentiment.txt",
  "--eval-batch-size": "32",
  "--ffn-lr": "0.001",
  "--help": false,
  "--lang": "English",
  "--loss-type": "cross-entropy",
  "--max-epoch": "20",
  "--max-length": "128",
  "--output-dropout": "0.1",
  "--seed": "42",
  "--train-batch-size": "32",
  "--train-path": "E:\\Spanemotion\\SpanEmo-master\\SpanEmo-LIWC\\data-feature\\train-sentiment.txt"
}{
  "--alpha-loss": "0.2",
  "--bert-lr": "2e-5",
  "--checkpoint-path": "2022-07-25-21:00:50.pt",
  "--dev-path": "E:\\Spanemotion\\SpanEmo-master\\SpanEmo-LIWC\\data-feature\\dev-sentiment.txt",
  "--eval-batch-size": "32",
  "--ffn-lr": "0.001",
  "--help": false,
  "--lang": "English",
  "--loss-type": "cross-entropy",
  "--max-epoch": "20",
  "--max-length": "128",
  "--output-dropout": "0.1",
  "--seed": "42",
  "--train-batch-size": "16",
  "--train-path": "E:\\Spanemotion\\SpanEmo-master\\SpanEmo-LIWC\\data-feature\\train-sentiment.txt"
}{
  "--alpha-loss": "0.2",
  "--bert-lr": "2e-5",
  "--checkpoint-path": "2022-07-25-21:02:03.pt",
  "--dev-path": "E:\\Spanemotion\\SpanEmo-master\\SpanEmo-LIWC\\data-feature\\dev-sentiment.txt",
  "--eval-batch-size": "32",
  "--ffn-lr": "0.001",
  "--help": false,
  "--lang": "English",
  "--loss-type": "cross-entropy",
  "--max-epoch": "20",
  "--max-length": "128",
  "--output-dropout": "0.1",
  "--seed": "42",
  "--train-batch-size": "4",
  "--train-path": "E:\\Spanemotion\\SpanEmo-master\\SpanEmo-LIWC\\data-feature\\train-sentiment.txt"
}{
  "--alpha-loss": "0.2",
  "--bert-lr": "2e-5",
  "--checkpoint-path": "2022-07-25-21:14:14.pt",
  "--dev-path": "E:\\Spanemotion\\SpanEmo-master\\SpanEmo-LIWC\\data-feature\\dev.txt",
  "--eval-batch-size": "32",
  "--ffn-lr": "0.001",
  "--help": false,
  "--lang": "English",
  "--loss-type": "cross-entropy",
  "--max-epoch": "20",
  "--max-length": "128",
  "--output-dropout": "0.1",
  "--seed": "42",
  "--train-batch-size": "4",
  "--train-path": "E:\\Spanemotion\\SpanEmo-master\\SpanEmo-LIWC\\data-feature\\train.txt"
}{
  "--alpha-loss": "0.2",
  "--bert-lr": "2e-5",
  "--checkpoint-path": "2022-07-25-21:27:04.pt",
  "--dev-path": "E:\\Spanemotion\\SpanEmo-master\\SpanEmo-LIWC\\data-feature\\dev-feaword.txt",
  "--eval-batch-size": "32",
  "--ffn-lr": "0.001",
  "--help": false,
  "--lang": "English",
  "--loss-type": "cross-entropy",
  "--max-epoch": "20",
  "--max-length": "128",
  "--output-dropout": "0.1",
  "--seed": "42",
  "--train-batch-size": "4",
  "--train-path": "E:\\Spanemotion\\SpanEmo-master\\SpanEmo-LIWC\\data-feature\\train-feaword.txt"
}{
  "--alpha-loss": "0.2",
  "--bert-lr": "2e-5",
  "--checkpoint-path": "2022-08-06-21:46:54.pt",
  "--dev-path": "E:\\Spanemotion\\SpanEmo-master\\SpanEmo-LIWC\\data-feature\\dev-feature.txt",
  "--eval-batch-size": "32",
  "--ffn-lr": "0.001",
  "--help": false,
  "--lang": "English",
  "--loss-type": "cross-entropy",
  "--max-epoch": "20",
  "--max-length": "128",
  "--output-dropout": "0.1",
  "--seed": "42",
  "--train-batch-size": "4",
  "--train-path": "E:\\Spanemotion\\SpanEmo-master\\SpanEmo-LIWC\\data-feature\\train-feature.txt"
}{
  "--alpha-loss": "0.2",
  "--bert-lr": "2e-5",
  "--checkpoint-path": "2022-08-06-21:48:21.pt",
  "--dev-path": "E:\\Spanemotion\\SpanEmo-master\\SpanEmo-LIWC\\data-feature\\dev-sentiment.txt",
  "--eval-batch-size": "32",
  "--ffn-lr": "0.001",
  "--help": false,
  "--lang": "English",
  "--loss-type": "cross-entropy",
  "--max-epoch": "20",
  "--max-length": "128",
  "--output-dropout": "0.1",
  "--seed": "42",
  "--train-batch-size": "4",
  "--train-path": "E:\\Spanemotion\\SpanEmo-master\\SpanEmo-LIWC\\data-feature\\train-sentiment.txt"
}{
  "--alpha-loss": "0.2",
  "--bert-lr": "2e-5",
  "--checkpoint-path": "2022-08-29-16:50:08.pt",
  "--dev-path": "E:\\Spanemotion\\SpanEmo-master\\SpanEmo-LIWC\\data-feature\\dev-sentiment.txt",
  "--eval-batch-size": "32",
  "--ffn-lr": "0.001",
  "--help": false,
  "--lang": "English",
  "--loss-type": "cross-entropy",
  "--max-epoch": "20",
  "--max-length": "128",
  "--output-dropout": "0.1",
  "--seed": "42",
  "--train-batch-size": "4",
  "--train-path": "E:\\Spanemotion\\SpanEmo-master\\SpanEmo-LIWC\\data-feature\\train-sentiment.txt"
}{
  "--alpha-loss": "0.2",
  "--bert-lr": "2e-5",
  "--checkpoint-path": "2022-08-29-16:53:50.pt",
  "--dev-path": "E:\\Spanemotion\\SpanEmo-master\\SpanEmo-LIWC\\data-feature\\dev-sentiment.txt",
  "--eval-batch-size": "32",
  "--ffn-lr": "0.001",
  "--help": false,
  "--lang": "English",
  "--loss-type": "cross-entropy",
  "--max-epoch": "20",
  "--max-length": "128",
  "--output-dropout": "0.1",
  "--seed": "42",
  "--train-batch-size": "4",
  "--train-path": "E:\\Spanemotion\\SpanEmo-master\\SpanEmo-LIWC\\data-feature\\train-sentiment.txt"
}{
  "--alpha-loss": "0.2",
  "--bert-lr": "2e-5",
  "--checkpoint-path": "2022-08-29-16:58:20.pt",
  "--dev-path": "E:\\Spanemotion\\SpanEmo-master\\SpanEmo-LIWC\\data-feature\\dev-sentiment.txt",
  "--eval-batch-size": "32",
  "--ffn-lr": "0.001",
  "--help": false,
  "--lang": "English",
  "--loss-type": "cross-entropy",
  "--max-epoch": "20",
  "--max-length": "128",
  "--output-dropout": "0.1",
  "--seed": "42",
  "--train-batch-size": "4",
  "--train-path": "E:\\Spanemotion\\SpanEmo-master\\SpanEmo-LIWC\\data-feature\\train-sentiment.txt"
}{
  "--alpha-loss": "0.2",
  "--bert-lr": "2e-5",
  "--checkpoint-path": "2022-08-29-17:02:05.pt",
  "--dev-path": "E:\\Spanemotion\\SpanEmo-master\\SpanEmo-LIWC\\data-feature\\dev-sentiment.txt",
  "--eval-batch-size": "32",
  "--ffn-lr": "0.001",
  "--help": false,
  "--lang": "English",
  "--loss-type": "cross-entropy",
  "--max-epoch": "20",
  "--max-length": "128",
  "--output-dropout": "0.1",
  "--seed": "42",
  "--train-batch-size": "4",
  "--train-path": "E:\\Spanemotion\\SpanEmo-master\\SpanEmo-LIWC\\data-feature\\train-sentiment.txt"
}{
  "--alpha-loss": "0.2",
  "--bert-lr": "2e-5",
  "--checkpoint-path": "2022-08-29-18:04:49.pt",
  "--dev-path": "E:\\pythonProject\\Confusion-all\\data\\Group A\\post.csv",
  "--eval-batch-size": "32",
  "--ffn-lr": "0.001",
  "--help": false,
  "--lang": "English",
  "--loss-type": "cross-entropy",
  "--max-epoch": "20",
  "--max-length": "128",
  "--output-dropout": "0.1",
  "--seed": "42",
  "--train-batch-size": "4",
  "--train-path": "E:\\pythonProject\\Confusion-all\\data\\Group A\\post.csv"
}{
  "--alpha-loss": "0.2",
  "--bert-lr": "2e-5",
  "--checkpoint-path": "2022-08-29-18:12:08.pt",
  "--dev-path": "E:\\pythonProject\\Confusion-all\\data\\Group A\\post.csv",
  "--eval-batch-size": "32",
  "--ffn-lr": "0.001",
  "--help": false,
  "--lang": "English",
  "--loss-type": "cross-entropy",
  "--max-epoch": "20",
  "--max-length": "128",
  "--output-dropout": "0.1",
  "--seed": "42",
  "--train-batch-size": "4",
  "--train-path": "E:\\pythonProject\\Confusion-all\\data\\Group A\\post.csv"
}{
  "--alpha-loss": "0.2",
  "--bert-lr": "2e-5",
  "--checkpoint-path": "2022-08-29-18:44:04.pt",
  "--dev-path": "E:\\pythonProject\\Confusion-all\\data\\Group A\\dev-sentiment.txt",
  "--eval-batch-size": "32",
  "--ffn-lr": "0.001",
  "--help": false,
  "--lang": "English",
  "--loss-type": "cross-entropy",
  "--max-epoch": "20",
  "--max-length": "128",
  "--output-dropout": "0.1",
  "--seed": "42",
  "--train-batch-size": "4",
  "--train-path": "E:\\pythonProject\\Confusion-all\\data\\Group A\\train-sentiment.txt"
}{
  "--alpha-loss": "0.2",
  "--bert-lr": "2e-5",
  "--checkpoint-path": "2022-08-29-18:47:13.pt",
  "--dev-path": "E:\\pythonProject\\Confusion-all\\data\\Group A\\dev-sentiment.txt",
  "--eval-batch-size": "32",
  "--ffn-lr": "0.001",
  "--help": false,
  "--lang": "English",
  "--loss-type": "cross-entropy",
  "--max-epoch": "20",
  "--max-length": "128",
  "--output-dropout": "0.1",
  "--seed": "42",
  "--train-batch-size": "4",
  "--train-path": "E:\\pythonProject\\Confusion-all\\data\\Group A\\train-sentiment.txt"
}{
  "--alpha-loss": "0.2",
  "--bert-lr": "2e-5",
  "--checkpoint-path": "2022-08-29-18:48:11.pt",
  "--dev-path": "E:\\pythonProject\\Confusion-all\\data\\Group A\\dev-sentiment.txt",
  "--eval-batch-size": "32",
  "--ffn-lr": "0.001",
  "--help": false,
  "--lang": "English",
  "--loss-type": "cross-entropy",
  "--max-epoch": "20",
  "--max-length": "128",
  "--output-dropout": "0.1",
  "--seed": "42",
  "--train-batch-size": "4",
  "--train-path": "E:\\pythonProject\\Confusion-all\\data\\Group A\\train-sentiment.txt"
}{
  "--alpha-loss": "0.2",
  "--bert-lr": "2e-5",
  "--checkpoint-path": "2022-08-29-21:00:54.pt",
  "--dev-path": "E:\\pythonProject\\Confusion-all\\data\\Group A\\post.csv",
  "--eval-batch-size": "32",
  "--ffn-lr": "0.001",
  "--help": false,
  "--lang": "English",
  "--loss-type": "cross-entropy",
  "--max-epoch": "20",
  "--max-length": "128",
  "--output-dropout": "0.1",
  "--seed": "42",
  "--train-batch-size": "4",
  "--train-path": "E:\\pythonProject\\Confusion-all\\data\\Group A\\post.csv"
}{
  "--alpha-loss": "0.2",
  "--bert-lr": "2e-5",
  "--checkpoint-path": "2022-08-29-21:49:52.pt",
  "--dev-path": "E:\\pythonProject\\Confusion-all\\data\\Group A\\post.csv",
  "--eval-batch-size": "32",
  "--ffn-lr": "0.001",
  "--help": false,
  "--lang": "English",
  "--loss-type": "cross-entropy",
  "--max-epoch": "20",
  "--max-length": "128",
  "--output-dropout": "0.1",
  "--seed": "42",
  "--train-batch-size": "4",
  "--train-path": "E:\\pythonProject\\Confusion-all\\data\\Group A\\post.csv"
}{
  "--alpha-loss": "0.2",
  "--bert-lr": "2e-5",
  "--checkpoint-path": "2022-08-29-23:41:29.pt",
  "--dev-path": "E:\\pythonProject\\Confusion-all\\data\\Group A\\post.csv",
  "--eval-batch-size": "32",
  "--ffn-lr": "0.001",
  "--help": false,
  "--lang": "English",
  "--loss-type": "cross-entropy",
  "--max-epoch": "20",
  "--max-length": "128",
  "--output-dropout": "0.1",
  "--seed": "42",
  "--train-batch-size": "4",
  "--train-path": "E:\\pythonProject\\Confusion-all\\data\\Group A\\post.csv"
}{
  "--alpha-loss": "0.2",
  "--bert-lr": "2e-5",
  "--checkpoint-path": "2022-08-30-00:02:03.pt",
  "--dev-path": "E:\\pythonProject\\Confusion-all\\data\\Group A\\post.csv",
  "--eval-batch-size": "32",
  "--ffn-lr": "0.001",
  "--help": false,
  "--lang": "English",
  "--loss-type": "cross-entropy",
  "--max-epoch": "20",
  "--max-length": "128",
  "--output-dropout": "0.1",
  "--seed": "42",
  "--train-batch-size": "4",
  "--train-path": "E:\\pythonProject\\Confusion-all\\data\\Group A\\post.csv"
}{
  "--alpha-loss": "0.2",
  "--bert-lr": "2e-5",
  "--checkpoint-path": "2022-08-30-00:20:22.pt",
  "--dev-path": "E:\\pythonProject\\Confusion-all\\data\\Group A\\post.csv",
  "--eval-batch-size": "32",
  "--ffn-lr": "0.001",
  "--help": false,
  "--lang": "English",
  "--loss-type": "cross-entropy",
  "--max-epoch": "20",
  "--max-length": "128",
  "--output-dropout": "0.1",
  "--seed": "42",
  "--train-batch-size": "4",
  "--train-path": "E:\\pythonProject\\Confusion-all\\data\\Group A\\post.csv"
}